{"inkVersion":21,"root":[[["done",{"#f":5,"#n":"g-0"}],null],"done",{"manong_guard":[["^Good morning. Transaction?","\n","ev","str","^Polite","/str","/ev",{"*":".^.c-0","flg":20},"ev","str","^Confused","/str","/ev",{"*":".^.c-1","flg":20},"ev","str","^Silent","/str","/ev",{"*":".^.c-2","flg":20},{"c-0":["^ Good morning, sir. Incoming First Year. I'm here for enrollment.","\n",{"->":"id_check"},{"#f":5}],"c-1":["^ Is this the entrance for the New Admin building?","\n",{"->":"id_check"},{"#f":5}],"c-2":["^ (Just hand over papers)","\n",{"->":"id_check"},{"#f":5}]}],{"#f":1}],"id_check":["^ID?","\n","^I don't have a UP ID yet. Here is my Notice of Admission.","\n","^Freshie. Sige. Since you don't have an ID, logbook muna. (He points to the logbook on the ledge.) Write legibly. Time in. Purpose: \"Medical & Enrollment.\" Leave a valid ID card here, claim it when you exit.","\n","end",{"#f":1}],"#f":1}],"listDefs":{}}